odoo/addons/edi_voxel_account_invoice/README.rst
odoo/addons/edi_voxel_account_invoice/__init__.py
odoo/addons/edi_voxel_account_invoice/__manifest__.py
odoo/addons/edi_voxel_account_invoice/data/ir_cron_data.xml
odoo/addons/edi_voxel_account_invoice/i18n/edi_voxel_account_invoice.pot
odoo/addons/edi_voxel_account_invoice/i18n/es.po
odoo/addons/edi_voxel_account_invoice/migrations/13.0.1.0.0/post-migration.py
odoo/addons/edi_voxel_account_invoice/migrations/13.0.1.0.0/pre-migration.py
odoo/addons/edi_voxel_account_invoice/models/__init__.py
odoo/addons/edi_voxel_account_invoice/models/account_move.py
odoo/addons/edi_voxel_account_invoice/models/res_company.py
odoo/addons/edi_voxel_account_invoice/models/res_config_settings.py
odoo/addons/edi_voxel_account_invoice/readme/CONFIGURE.rst
odoo/addons/edi_voxel_account_invoice/readme/CONTRIBUTORS.rst
odoo/addons/edi_voxel_account_invoice/readme/DESCRIPTION.rst
odoo/addons/edi_voxel_account_invoice/readme/USAGE.rst
odoo/addons/edi_voxel_account_invoice/reports/__init__.py
odoo/addons/edi_voxel_account_invoice/reports/report_voxel_invoice.py
odoo/addons/edi_voxel_account_invoice/static/description/icon.png
odoo/addons/edi_voxel_account_invoice/static/description/index.html
odoo/addons/edi_voxel_account_invoice/tests/__init__.py
odoo/addons/edi_voxel_account_invoice/tests/test_voxel_account_invoice.py
odoo/addons/edi_voxel_account_invoice/views/account_move_views.xml
odoo/addons/edi_voxel_account_invoice/views/report_voxel_invoice.xml
odoo/addons/edi_voxel_account_invoice/views/res_company_view.xml
odoo/addons/edi_voxel_account_invoice/views/res_config_settings_views.xml
odoo13_addon_edi_voxel_account_invoice-13.0.1.1.3.dist-info/METADATA
odoo13_addon_edi_voxel_account_invoice-13.0.1.1.3.dist-info/WHEEL
odoo13_addon_edi_voxel_account_invoice-13.0.1.1.3.dist-info/top_level.txt
odoo13_addon_edi_voxel_account_invoice-13.0.1.1.3.dist-info/RECORD
